SudsLibrary/__init__.py
SudsLibrary/clientmanagement.py
SudsLibrary/factory.py
SudsLibrary/monkeypatches.py
SudsLibrary/options.py
SudsLibrary/proxy.py
SudsLibrary/soaplogging.py
SudsLibrary/utils.py
SudsLibrary/version.py
SudsLibrary/wsse.py
robotframework_sudslibrary_aljcalandra-1.1.4.dist-info/LICENSE.txt
robotframework_sudslibrary_aljcalandra-1.1.4.dist-info/METADATA
robotframework_sudslibrary_aljcalandra-1.1.4.dist-info/WHEEL
robotframework_sudslibrary_aljcalandra-1.1.4.dist-info/top_level.txt
robotframework_sudslibrary_aljcalandra-1.1.4.dist-info/zip-safe
robotframework_sudslibrary_aljcalandra-1.1.4.dist-info/RECORD
